sure_tosca_client/__init__.py
sure_tosca_client/api_client.py
sure_tosca_client/configuration.py
sure_tosca_client/rest.py
sure_tosca_client/api/__init__.py
sure_tosca_client/api/default_api.py
sure_tosca_client/models/__init__.py
sure_tosca_client/models/node_template.py
sure_tosca_client/models/node_template_map.py
sure_tosca_client/models/topology_template.py
sure_tosca_client/models/tosca_template.py
test/__init__.py
test/test_default_api.py
test/test_node_template.py
test/test_node_template_map.py
test/test_topology_template.py
test/test_tosca_template.py
sure_tosca_client-1.0.6.dist-info/METADATA
sure_tosca_client-1.0.6.dist-info/WHEEL
sure_tosca_client-1.0.6.dist-info/top_level.txt
sure_tosca_client-1.0.6.dist-info/RECORD
