Metadata-Version: 2.1
Name: sure-tosca-client
Version: 1.0.6
Summary: This is a python client for the sure_tosca REST service
Home-page: https://github.com/qcdis-sdia/sdia-sure_tosca-client
Author-email: S.Koulouzis@uva.nl
License: UNKNOWN
Keywords: Swagger,tosca-sure
Platform: UNKNOWN
Classifier: Programming Language :: Python :: 3
Classifier: License :: OSI Approved :: Apache Software License
Classifier: Operating System :: OS Independent
Requires-Python: >=3.7
Requires-Dist: certifi (==2020.4.5.1)
Requires-Dist: six (==1.14.0)
Requires-Dist: setuptools (==46.1.3)
Requires-Dist: urllib3 (==1.25.8)
Requires-Dist: numpy (==1.18.2)
